README
setup.py
autoreport/__init__.py
autoreport/admin.py
autoreport/forms.py
autoreport/models.py
autoreport/urls.py
autoreport/views.py
autoreport.egg-info/PKG-INFO
autoreport.egg-info/SOURCES.txt
autoreport.egg-info/dependency_links.txt
autoreport.egg-info/requires.txt
autoreport.egg-info/top_level.txt