Metadata-Version: 1.0
Name: autoreport
Version: 0.1
Summary: Self-made relatorio reports for Django
Home-page: http://github.com/terrex/autoreport
Author: Guillermo Gutiérrez
Author-email: xiterrex@gmail.com
License: GPL
Platform: UNKNOWN
Classifier: Development Status :: 4 - Beta
Classifier: Framework :: Django
Classifier: License :: OSI Approved :: GNU General Public License (GPL)
Classifier: Topic :: Text Processing :: Markup
Classifier: Topic :: Text Processing :: Markup :: XML
